py_myaskapi/__init__.py
py_myaskapi-1.0.0.dist-info/LICENSE
py_myaskapi-1.0.0.dist-info/METADATA
py_myaskapi-1.0.0.dist-info/WHEEL
py_myaskapi-1.0.0.dist-info/top_level.txt
py_myaskapi-1.0.0.dist-info/RECORD
