Metadata-Version: 2.1
Name: py-myaskapi
Version: 1.0.0
Summary: Simple interface to the MyAsk API.
Home-page: https://github.com/edmenendez/py-myaskapi
Author: Ed Menendez
Author-email: ed@menendez.com
Classifier: Programming Language :: Python :: 3
Classifier: License :: OSI Approved :: MIT License
Classifier: Operating System :: OS Independent
Requires-Python: >=3.6
License-File: LICENSE
Requires-Dist: requests
